odoo/addons/carrier_restrict_connection/README.rst
odoo/addons/carrier_restrict_connection/__init__.py
odoo/addons/carrier_restrict_connection/__manifest__.py
odoo/addons/carrier_restrict_connection/i18n/es.po
odoo/addons/carrier_restrict_connection/models/__init__.py
odoo/addons/carrier_restrict_connection/models/delivery_carrier.py
odoo/addons/carrier_restrict_connection/models/stock_picking_type.py
odoo/addons/carrier_restrict_connection/readme/CONFIGURE.md
odoo/addons/carrier_restrict_connection/readme/CONTRIBUTORS.md
odoo/addons/carrier_restrict_connection/readme/DESCRIPTION.md
odoo/addons/carrier_restrict_connection/readme/USAGE.md
odoo/addons/carrier_restrict_connection/static/description/icon.png
odoo/addons/carrier_restrict_connection/static/description/index.html
odoo/addons/carrier_restrict_connection/tests/__init__.py
odoo/addons/carrier_restrict_connection/tests/test_carrier_restrict_connection.py
odoo/addons/carrier_restrict_connection/views/stock_picking_views.xml
odoo_addon_carrier_restrict_connection-17.0.1.0.0.3.dist-info/METADATA
odoo_addon_carrier_restrict_connection-17.0.1.0.0.3.dist-info/WHEEL
odoo_addon_carrier_restrict_connection-17.0.1.0.0.3.dist-info/top_level.txt
odoo_addon_carrier_restrict_connection-17.0.1.0.0.3.dist-info/RECORD
